{
    "joints": [
        {
            "jointName": "Hand_Start",
            "parentJointName": "Invalid",
            "position": {
                "x": 0.0,
                "y": 0.0,
                "z": 0.0
            },
            "rotation": {
                "x": 1.4901162970204497e-8,
                "y": 1.0,
                "z": 0.0,
                "w": 7.450581485102248e-9
            }
        },
        {
            "jointName": "Hand_WristRoot",
            "parentJointName": "Hand_WristRoot",
            "position": {
                "x": 0.0,
                "y": 0.0,
                "z": 0.0
            },
            "rotation": {
                "x": 0.0,
                "y": 0.0,
                "z": 0.0,
                "w": 1.0
            }
        },
        {
            "jointName": "Hand_Thumb0",
            "parentJointName": "Hand_WristRoot",
            "position": {
                "x": 0.020068995654582979,
                "y": -0.011553998105227948,
                "z": 0.010496998205780983
            },
            "rotation": {
                "x": 0.4175246059894562,
                "y": -0.3797653019428253,
                "z": -0.07649960368871689,
                "w": 0.8219485282897949
            }
        },
        {
            "jointName": "Hand_Thumb1",
            "parentJointName": "Hand_Thumb0",
            "position": {
                "x": 0.02485242672264576,
                "y": -4.637986421585083e-7,
                "z": -3.2316893339157107e-7
            },
            "rotation": {
                "x": 0.29651275277137759,
                "y": -0.04908505454659462,
                "z": -0.13569548726081849,
                "w": 0.9440644383430481
            }
        },
        {
            "jointName": "Hand_Thumb2",
            "parentJointName": "Hand_Thumb1",
            "position": {
                "x": 0.03251289948821068,
                "y": -6.51925802230835e-9,
                "z": -4.423782229423523e-9
            },
            "rotation": {
                "x": -0.08184285461902619,
                "y": 0.05138880014419556,
                "z": -0.2075071483850479,
                "w": 0.9734483957290649
            }
        },
        {
            "jointName": "Hand_Thumb3",
            "parentJointName": "Hand_Thumb2",
            "position": {
                "x": 0.03379308432340622,
                "y": -7.450580596923828e-9,
                "z": 0.0
            },
            "rotation": {
                "x": 0.08231061697006226,
                "y": -0.060335204005241397,
                "z": 0.00016245245933532715,
                "w": 0.9947787523269653
            }
        },
        {
            "jointName": "Hand_Index1",
            "parentJointName": "Hand_WristRoot",
            "position": {
                "x": 0.09599620848894119,
                "y": -0.007316452916711569,
                "z": 0.023550670593976976
            },
            "rotation": {
                "x": 0.03548254072666168,
                "y": 0.015286623500287533,
                "z": -0.2988879978656769,
                "w": 0.95350581407547
            }
        },
        {
            "jointName": "Hand_Index2",
            "parentJointName": "Hand_Index1",
            "position": {
                "x": 0.03792726248502731,
                "y": -1.3969838619232178e-9,
                "z": -5.587935447692871e-9
            },
            "rotation": {
                "x": -0.025717590004205705,
                "y": -0.0038956589996814729,
                "z": -0.40542900562286379,
                "w": 0.9137564301490784
            }
        },
        {
            "jointName": "Hand_Index3",
            "parentJointName": "Hand_Index2",
            "position": {
                "x": 0.024303629994392396,
                "y": 3.4924596548080446e-10,
                "z": -3.725290298461914e-9
            },
            "rotation": {
                "x": -0.017068825662136079,
                "y": 0.022599350661039354,
                "z": -0.18214312195777894,
                "w": 0.9828641414642334
            }
        },
        {
            "jointName": "Hand_Middle1",
            "parentJointName": "Hand_WristRoot",
            "position": {
                "x": 0.09564658254384995,
                "y": -0.0025431537069380285,
                "z": 0.0017259027808904648
            },
            "rotation": {
                "x": -0.02524547465145588,
                "y": 0.0576450377702713,
                "z": -0.33505550026893618,
                "w": 0.9400944113731384
            }
        },
        {
            "jointName": "Hand_Middle2",
            "parentJointName": "Hand_Middle1",
            "position": {
                "x": 0.04292696714401245,
                "y": -4.656612873077393e-10,
                "z": 1.862645149230957e-9
            },
            "rotation": {
                "x": -0.012943565845489502,
                "y": -0.0013251359341666103,
                "z": -0.4616350531578064,
                "w": 0.8869744539260864
            }
        },
        {
            "jointName": "Hand_Middle3",
            "parentJointName": "Hand_Middle2",
            "position": {
                "x": 0.027549564838409425,
                "y": -9.313225746154786e-10,
                "z": 0.0
            },
            "rotation": {
                "x": -0.07016022503376007,
                "y": -0.012141793966293335,
                "z": -0.29014694690704348,
                "w": 0.9543296098709106
            }
        },
        {
            "jointName": "Hand_Ring1",
            "parentJointName": "Hand_WristRoot",
            "position": {
                "x": 0.088693767786026,
                "y": -0.006529305595904589,
                "z": -0.017465239390730859
            },
            "rotation": {
                "x": -0.08355221897363663,
                "y": 0.09558528661727905,
                "z": -0.3469109833240509,
                "w": 0.9292660355567932
            }
        },
        {
            "jointName": "Hand_Ring2",
            "parentJointName": "Hand_Ring1",
            "position": {
                "x": 0.03899606317281723,
                "y": -1.3969838619232178e-9,
                "z": -7.450580596923828e-9
            },
            "rotation": {
                "x": -0.04150571674108505,
                "y": -0.013492152094841004,
                "z": -0.4805864989757538,
                "w": 0.8758606314659119
            }
        },
        {
            "jointName": "Hand_Ring3",
            "parentJointName": "Hand_Ring2",
            "position": {
                "x": 0.02657337486743927,
                "y": -3.259629011154175e-9,
                "z": 2.7939677238464357e-9
            },
            "rotation": {
                "x": -0.020517880097031595,
                "y": -0.02910851128399372,
                "z": -0.3442618250846863,
                "w": 0.9381980299949646
            }
        },
        {
            "jointName": "Hand_Pinky0",
            "parentJointName": "Hand_WristRoot",
            "position": {
                "x": 0.034073542803525928,
                "y": -0.009419831447303296,
                "z": -0.022998567670583726
            },
            "rotation": {
                "x": -0.20703598856925965,
                "y": 0.1403428316116333,
                "z": -0.01831180788576603,
                "w": 0.968041718006134
            }
        },
        {
            "jointName": "Hand_Pinky1",
            "parentJointName": "Hand_Pinky0",
            "position": {
                "x": 0.04565052315592766,
                "y": -0.0000010016374289989472,
                "z": 0.0000022025778889656069
            },
            "rotation": {
                "x": 0.06261370331048966,
                "y": 0.06191007047891617,
                "z": -0.3061663508415222,
                "w": 0.9478970766067505
            }
        },
        {
            "jointName": "Hand_Pinky2",
            "parentJointName": "Hand_Pinky1",
            "position": {
                "x": 0.03072037547826767,
                "y": 1.862645149230957e-9,
                "z": 0.0
            },
            "rotation": {
                "x": -0.07589368522167206,
                "y": 0.018677838146686555,
                "z": -0.4768593907356262,
                "w": 0.8754978179931641
            }
        },
        {
            "jointName": "Hand_Pinky3",
            "parentJointName": "Hand_Pinky2",
            "position": {
                "x": 0.020311348140239717,
                "y": -1.862645149230957e-9,
                "z": 3.725290298461914e-9
            },
            "rotation": {
                "x": 0.0018223300576210023,
                "y": -0.04618951678276062,
                "z": -0.3290872573852539,
                "w": 0.9431674480438232
            }
        },
        {
            "jointName": "Hand_ThumbTip",
            "parentJointName": "Hand_Thumb3",
            "position": {
                "x": 0.024590760469436647,
                "y": 0.0010269805788993836,
                "z": -0.0006703690160065889
            },
            "rotation": {
                "x": 0.0,
                "y": -2.9802315282267956e-8,
                "z": 1.4901157641133978e-8,
                "w": 1.0
            }
        },
        {
            "jointName": "Hand_IndexTip",
            "parentJointName": "Hand_Index3",
            "position": {
                "x": 0.022363364696502687,
                "y": 0.001025073230266571,
                "z": -0.00029561296105384827
            },
            "rotation": {
                "x": 0.0,
                "y": -1.4901161193847657e-8,
                "z": 2.9802322387695315e-8,
                "w": 1.0
            }
        },
        {
            "jointName": "Hand_MiddleTip",
            "parentJointName": "Hand_Middle3",
            "position": {
                "x": 0.02496488392353058,
                "y": 0.001137303188443184,
                "z": -0.00030865520238876343
            },
            "rotation": {
                "x": 3.725290298461914e-9,
                "y": -7.450580596923828e-9,
                "z": -2.9802322387695315e-8,
                "w": 1.0
            }
        },
        {
            "jointName": "Hand_RingTip",
            "parentJointName": "Hand_Ring3",
            "position": {
                "x": 0.02432611584663391,
                "y": 0.0016081708017736674,
                "z": -0.000257907435297966
            },
            "rotation": {
                "x": 4.656612428988183e-9,
                "y": -1.4901159417490817e-8,
                "z": 0.0,
                "w": 1.0
            }
        },
        {
            "jointName": "Hand_PinkyTip",
            "parentJointName": "Hand_Pinky3",
            "position": {
                "x": 0.02192234992980957,
                "y": 0.001216089352965355,
                "z": 0.00024647824466228485
            },
            "rotation": {
                "x": -3.725290298461914e-9,
                "y": 0.0,
                "z": 0.0,
                "w": 1.0
            }
        }
    ]
}