{
    "joints": [
        {
            "jointName": "Hand_Start",
            "parentJointName": "Invalid",
            "position": {
                "x": 0.0,
                "y": 0.0,
                "z": 0.0
            },
            "rotation": {
                "x": 0.0,
                "y": 1.0,
                "z": 0.0,
                "w": 0.0
            }
        },
        {
            "jointName": "Hand_WristRoot",
            "parentJointName": "Hand_WristRoot",
            "position": {
                "x": 0.0,
                "y": 0.0,
                "z": 0.0
            },
            "rotation": {
                "x": 0.0,
                "y": 0.0,
                "z": 0.0,
                "w": 1.0
            }
        },
        {
            "jointName": "Hand_Thumb0",
            "parentJointName": "Hand_WristRoot",
            "position": {
                "x": 0.020068995654582979,
                "y": -0.011553998105227948,
                "z": 0.010496998205780983
            },
            "rotation": {
                "x": 0.42544299364089968,
                "y": -0.36941322684288027,
                "z": -0.09297521412372589,
                "w": 0.8209066987037659
            }
        },
        {
            "jointName": "Hand_Thumb1",
            "parentJointName": "Hand_Thumb0",
            "position": {
                "x": 0.02485242672264576,
                "y": -4.637986421585083e-7,
                "z": -3.2316893339157107e-7
            },
            "rotation": {
                "x": 0.30106982588768008,
                "y": -0.09490075707435608,
                "z": -0.15069988369941712,
                "w": 0.93682461977005
            }
        },
        {
            "jointName": "Hand_Thumb2",
            "parentJointName": "Hand_Thumb1",
            "position": {
                "x": 0.03251289948821068,
                "y": -6.51925802230835e-9,
                "z": -4.423782229423523e-9
            },
            "rotation": {
                "x": -0.08264558017253876,
                "y": 0.057453956454992297,
                "z": -0.14428192377090455,
                "w": 0.9844040870666504
            }
        },
        {
            "jointName": "Hand_Thumb3",
            "parentJointName": "Hand_Thumb2",
            "position": {
                "x": 0.03379308432340622,
                "y": -7.450580596923828e-9,
                "z": 0.0
            },
            "rotation": {
                "x": 0.08246887475252152,
                "y": -0.06090689077973366,
                "z": 0.007125972770154476,
                "w": 0.9947052001953125
            }
        },
        {
            "jointName": "Hand_Index1",
            "parentJointName": "Hand_WristRoot",
            "position": {
                "x": 0.09599620848894119,
                "y": -0.007316452916711569,
                "z": 0.023550670593976976
            },
            "rotation": {
                "x": 0.02731885388493538,
                "y": 0.04429146274924278,
                "z": -0.3740226924419403,
                "w": 0.9259583950042725
            }
        },
        {
            "jointName": "Hand_Index2",
            "parentJointName": "Hand_Index1",
            "position": {
                "x": 0.03792726248502731,
                "y": -1.3969838619232178e-9,
                "z": -5.587935447692871e-9
            },
            "rotation": {
                "x": -0.026298703625798227,
                "y": 0.0003009999927598983,
                "z": -0.25758224725723269,
                "w": 0.9658983945846558
            }
        },
        {
            "jointName": "Hand_Index3",
            "parentJointName": "Hand_Index2",
            "position": {
                "x": 0.024303629994392396,
                "y": 3.4924596548080446e-10,
                "z": -3.725290298461914e-9
            },
            "rotation": {
                "x": -0.01684506982564926,
                "y": 0.024337956681847574,
                "z": -0.09567856043577194,
                "w": 0.9949721097946167
            }
        },
        {
            "jointName": "Hand_Middle1",
            "parentJointName": "Hand_WristRoot",
            "position": {
                "x": 0.09564658254384995,
                "y": -0.0025431537069380285,
                "z": 0.0017259027808904648
            },
            "rotation": {
                "x": -0.04591279849410057,
                "y": 0.060225747525691989,
                "z": -0.5731660723686218,
                "w": 0.8159322738647461
            }
        },
        {
            "jointName": "Hand_Middle2",
            "parentJointName": "Hand_Middle1",
            "position": {
                "x": 0.04292696714401245,
                "y": -4.656612873077393e-10,
                "z": 1.862645149230957e-9
            },
            "rotation": {
                "x": -0.012522564269602299,
                "y": -0.0047966004349291328,
                "z": -0.7024716734886169,
                "w": 0.7115854024887085
            }
        },
        {
            "jointName": "Hand_Middle3",
            "parentJointName": "Hand_Middle2",
            "position": {
                "x": 0.027549564838409425,
                "y": -9.313225746154786e-10,
                "z": 0.0
            },
            "rotation": {
                "x": -0.09095893055200577,
                "y": -0.024019109085202218,
                "z": -0.5604767203330994,
                "w": 0.8228095173835754
            }
        },
        {
            "jointName": "Hand_Ring1",
            "parentJointName": "Hand_WristRoot",
            "position": {
                "x": 0.088693767786026,
                "y": -0.006529305595904589,
                "z": -0.017465239390730859
            },
            "rotation": {
                "x": -0.09586310386657715,
                "y": 0.048186883330345157,
                "z": -0.6225743889808655,
                "w": 0.775170624256134
            }
        },
        {
            "jointName": "Hand_Ring2",
            "parentJointName": "Hand_Ring1",
            "position": {
                "x": 0.03899606317281723,
                "y": -1.3969838619232178e-9,
                "z": -7.450580596923828e-9
            },
            "rotation": {
                "x": -0.041711658239364627,
                "y": -0.02065807767212391,
                "z": -0.6814919710159302,
                "w": 0.7303438782691956
            }
        },
        {
            "jointName": "Hand_Ring3",
            "parentJointName": "Hand_Ring2",
            "position": {
                "x": 0.02657337486743927,
                "y": -3.259629011154175e-9,
                "z": 2.7939677238464357e-9
            },
            "rotation": {
                "x": -0.030108394101262094,
                "y": -0.026872863993048669,
                "z": -0.559653103351593,
                "w": 0.8277437090873718
            }
        },
        {
            "jointName": "Hand_Pinky0",
            "parentJointName": "Hand_WristRoot",
            "position": {
                "x": 0.034073542803525928,
                "y": -0.009419831447303296,
                "z": -0.022998567670583726
            },
            "rotation": {
                "x": -0.20703598856925965,
                "y": 0.14034287631511689,
                "z": -0.01831177808344364,
                "w": 0.968041718006134
            }
        },
        {
            "jointName": "Hand_Pinky1",
            "parentJointName": "Hand_Pinky0",
            "position": {
                "x": 0.04565052315592766,
                "y": -0.0000010016374289989472,
                "z": 0.0000022025778889656069
            },
            "rotation": {
                "x": 0.06713735312223435,
                "y": 0.025329165160655977,
                "z": -0.6062020659446716,
                "w": 0.7920669913291931
            }
        },
        {
            "jointName": "Hand_Pinky2",
            "parentJointName": "Hand_Pinky1",
            "position": {
                "x": 0.03072037547826767,
                "y": 1.862645149230957e-9,
                "z": 0.0
            },
            "rotation": {
                "x": -0.0864291712641716,
                "y": 0.006813280284404755,
                "z": -0.6502171158790588,
                "w": 0.7547856569290161
            }
        },
        {
            "jointName": "Hand_Pinky3",
            "parentJointName": "Hand_Pinky2",
            "position": {
                "x": 0.020311348140239717,
                "y": -1.862645149230957e-9,
                "z": 3.725290298461914e-9
            },
            "rotation": {
                "x": 0.002581638051196933,
                "y": -0.03977147862315178,
                "z": -0.5760433673858643,
                "w": 0.8164469599723816
            }
        },
        {
            "jointName": "Hand_ThumbTip",
            "parentJointName": "Hand_Thumb3",
            "position": {
                "x": 0.024590760469436647,
                "y": 0.0010269805788993836,
                "z": -0.0006703690160065889
            },
            "rotation": {
                "x": 7.450572603318051e-9,
                "y": -2.9802290413272204e-8,
                "z": 2.9802290413272204e-8,
                "w": 1.0
            }
        },
        {
            "jointName": "Hand_IndexTip",
            "parentJointName": "Hand_Index3",
            "position": {
                "x": 0.022363364696502687,
                "y": 0.001025073230266571,
                "z": -0.00029561296105384827
            },
            "rotation": {
                "x": 5.215402865133001e-8,
                "y": -4.0978164861371627e-8,
                "z": 0.0,
                "w": 1.0
            }
        },
        {
            "jointName": "Hand_MiddleTip",
            "parentJointName": "Hand_Middle3",
            "position": {
                "x": 0.02496488392353058,
                "y": 0.001137303188443184,
                "z": -0.00030865520238876343
            },
            "rotation": {
                "x": -3.7252860352054998e-8,
                "y": 0.0,
                "z": 0.0,
                "w": 1.0
            }
        },
        {
            "jointName": "Hand_RingTip",
            "parentJointName": "Hand_Ring3",
            "position": {
                "x": 0.02432611584663391,
                "y": 0.0016081708017736674,
                "z": -0.000257907435297966
            },
            "rotation": {
                "x": 0.0,
                "y": 0.0,
                "z": 2.9802286860558526e-8,
                "w": 1.0
            }
        },
        {
            "jointName": "Hand_PinkyTip",
            "parentJointName": "Hand_Pinky3",
            "position": {
                "x": 0.02192234992980957,
                "y": 0.001216089352965355,
                "z": 0.00024647824466228485
            },
            "rotation": {
                "x": 0.0,
                "y": 0.0,
                "z": 0.0,
                "w": 1.0
            }
        }
    ]
}