{
    "joints": [
        {
            "jointName": "Hand_Start",
            "parentJointName": "Invalid",
            "position": {
                "x": 0.0,
                "y": 0.0,
                "z": 0.0
            },
            "rotation": {
                "x": 0.0,
                "y": 1.0,
                "z": 0.0,
                "w": 3.7252889661942847e-9
            }
        },
        {
            "jointName": "Hand_WristRoot",
            "parentJointName": "Hand_WristRoot",
            "position": {
                "x": 0.0,
                "y": 0.0,
                "z": 0.0
            },
            "rotation": {
                "x": 0.0,
                "y": 0.0,
                "z": 0.0,
                "w": 1.0
            }
        },
        {
            "jointName": "Hand_Thumb0",
            "parentJointName": "Hand_WristRoot",
            "position": {
                "x": 0.020068995654582979,
                "y": -0.011553998105227948,
                "z": 0.010496998205780983
            },
            "rotation": {
                "x": 0.42200767993927,
                "y": -0.3739911913871765,
                "z": -0.08579974621534348,
                "w": 0.8213881850242615
            }
        },
        {
            "jointName": "Hand_Thumb1",
            "parentJointName": "Hand_Thumb0",
            "position": {
                "x": 0.02485242672264576,
                "y": -4.637986421585083e-7,
                "z": -3.2316893339157107e-7
            },
            "rotation": {
                "x": 0.3000664710998535,
                "y": -0.0609026700258255,
                "z": -0.1397707313299179,
                "w": 0.9416555166244507
            }
        },
        {
            "jointName": "Hand_Thumb2",
            "parentJointName": "Hand_Thumb1",
            "position": {
                "x": 0.03251289948821068,
                "y": -6.51925802230835e-9,
                "z": -4.423782229423523e-9
            },
            "rotation": {
                "x": -0.08200037479400635,
                "y": 0.05241333320736885,
                "z": -0.1970406323671341,
                "w": 0.9755530953407288
            }
        },
        {
            "jointName": "Hand_Thumb3",
            "parentJointName": "Hand_Thumb2",
            "position": {
                "x": 0.03379308432340622,
                "y": -7.450580596923828e-9,
                "z": 0.0
            },
            "rotation": {
                "x": 0.08091388642787934,
                "y": -0.05569213628768921,
                "z": -0.05511753261089325,
                "w": 0.993636429309845
            }
        },
        {
            "jointName": "Hand_Index1",
            "parentJointName": "Hand_WristRoot",
            "position": {
                "x": 0.09599620848894119,
                "y": -0.007316452916711569,
                "z": 0.023550670593976976
            },
            "rotation": {
                "x": 0.03466614708304405,
                "y": 0.026912780478596689,
                "z": -0.5047272443771362,
                "w": 0.8621626496315002
            }
        },
        {
            "jointName": "Hand_Index2",
            "parentJointName": "Hand_Index1",
            "position": {
                "x": 0.03792726248502731,
                "y": -1.3969838619232178e-9,
                "z": -5.587935447692871e-9
            },
            "rotation": {
                "x": -0.026325812563300134,
                "y": 0.0008243278716690838,
                "z": -0.23868167400360108,
                "w": 0.9707406759262085
            }
        },
        {
            "jointName": "Hand_Index3",
            "parentJointName": "Hand_Index2",
            "position": {
                "x": 0.024303629994392396,
                "y": 3.4924596548080446e-10,
                "z": -3.725290298461914e-9
            },
            "rotation": {
                "x": -0.016878237947821618,
                "y": 0.024142738431692125,
                "z": -0.1059054434299469,
                "w": 0.9939398169517517
            }
        },
        {
            "jointName": "Hand_Middle1",
            "parentJointName": "Hand_WristRoot",
            "position": {
                "x": 0.09564658254384995,
                "y": -0.0025431537069380285,
                "z": 0.0017259027808904648
            },
            "rotation": {
                "x": -0.04516677185893059,
                "y": 0.05667022243142128,
                "z": -0.5881065130233765,
                "w": 0.8055304884910584
            }
        },
        {
            "jointName": "Hand_Middle2",
            "parentJointName": "Hand_Middle1",
            "position": {
                "x": 0.04292696714401245,
                "y": -4.656612873077393e-10,
                "z": 1.862645149230957e-9
            },
            "rotation": {
                "x": -0.012758512049913407,
                "y": -0.0038417247124016287,
                "z": -0.6396077871322632,
                "w": 0.7685860395431519
            }
        },
        {
            "jointName": "Hand_Middle3",
            "parentJointName": "Hand_Middle2",
            "position": {
                "x": 0.027549564838409425,
                "y": -9.313225746154786e-10,
                "z": 0.0
            },
            "rotation": {
                "x": -0.08933412283658982,
                "y": -0.022981366142630578,
                "z": -0.536913275718689,
                "w": 0.8385793566703796
            }
        },
        {
            "jointName": "Hand_Ring1",
            "parentJointName": "Hand_WristRoot",
            "position": {
                "x": 0.088693767786026,
                "y": -0.006529305595904589,
                "z": -0.017465239390730859
            },
            "rotation": {
                "x": -0.09245627373456955,
                "y": 0.04514651000499725,
                "z": -0.6139293313026428,
                "w": 0.7826266884803772
            }
        },
        {
            "jointName": "Hand_Ring2",
            "parentJointName": "Hand_Ring1",
            "position": {
                "x": 0.03899606317281723,
                "y": -1.3969838619232178e-9,
                "z": -7.450580596923828e-9
            },
            "rotation": {
                "x": -0.04190899059176445,
                "y": -0.01887586899101734,
                "z": -0.632146418094635,
                "w": 0.7734845280647278
            }
        },
        {
            "jointName": "Hand_Ring3",
            "parentJointName": "Hand_Ring2",
            "position": {
                "x": 0.02657337486743927,
                "y": -3.259629011154175e-9,
                "z": 2.7939677238464357e-9
            },
            "rotation": {
                "x": -0.030544888228178026,
                "y": -0.026718512177467347,
                "z": -0.5696371793746948,
                "w": 0.8208938241004944
            }
        },
        {
            "jointName": "Hand_Pinky0",
            "parentJointName": "Hand_WristRoot",
            "position": {
                "x": 0.034073542803525928,
                "y": -0.009419831447303296,
                "z": -0.022998567670583726
            },
            "rotation": {
                "x": -0.20703594386577607,
                "y": 0.14034287631511689,
                "z": -0.018311822786927224,
                "w": 0.968041718006134
            }
        },
        {
            "jointName": "Hand_Pinky1",
            "parentJointName": "Hand_Pinky0",
            "position": {
                "x": 0.04565052315592766,
                "y": -0.0000010016374289989472,
                "z": 0.0000022025778889656069
            },
            "rotation": {
                "x": 0.06514786928892136,
                "y": 0.02821892686188221,
                "z": -0.561558187007904,
                "w": 0.8243857622146606
            }
        },
        {
            "jointName": "Hand_Pinky2",
            "parentJointName": "Hand_Pinky1",
            "position": {
                "x": 0.03072037547826767,
                "y": 1.862645149230957e-9,
                "z": 0.0
            },
            "rotation": {
                "x": -0.0850045308470726,
                "y": 0.008732223883271218,
                "z": -0.6244440674781799,
                "w": 0.7763811349868774
            }
        },
        {
            "jointName": "Hand_Pinky3",
            "parentJointName": "Hand_Pinky2",
            "position": {
                "x": 0.020311348140239717,
                "y": -1.862645149230957e-9,
                "z": 3.725290298461914e-9
            },
            "rotation": {
                "x": 0.00271197990514338,
                "y": -0.03809056431055069,
                "z": -0.6208941340446472,
                "w": 0.7829638123512268
            }
        },
        {
            "jointName": "Hand_ThumbTip",
            "parentJointName": "Hand_Thumb3",
            "position": {
                "x": 0.024590760469436647,
                "y": 0.0010269805788993836,
                "z": -0.0006703690160065889
            },
            "rotation": {
                "x": 3.725286745748235e-8,
                "y": -2.9802293965985883e-8,
                "z": 0.0,
                "w": 1.0
            }
        },
        {
            "jointName": "Hand_IndexTip",
            "parentJointName": "Hand_Index3",
            "position": {
                "x": 0.022363364696502687,
                "y": 0.001025073230266571,
                "z": -0.00029561296105384827
            },
            "rotation": {
                "x": -7.45057526785331e-9,
                "y": 1.559964246666823e-8,
                "z": 0.0,
                "w": 1.0
            }
        },
        {
            "jointName": "Hand_MiddleTip",
            "parentJointName": "Hand_Middle3",
            "position": {
                "x": 0.02496488392353058,
                "y": 0.001137303188443184,
                "z": -0.00030865520238876343
            },
            "rotation": {
                "x": -7.450572603318051e-9,
                "y": 0.0,
                "z": -2.9802290413272204e-8,
                "w": 1.0
            }
        },
        {
            "jointName": "Hand_RingTip",
            "parentJointName": "Hand_Ring3",
            "position": {
                "x": 0.02432611584663391,
                "y": 0.0016081708017736674,
                "z": -0.000257907435297966
            },
            "rotation": {
                "x": 0.0,
                "y": 0.0,
                "z": -2.9802293965985883e-8,
                "w": 1.0
            }
        },
        {
            "jointName": "Hand_PinkyTip",
            "parentJointName": "Hand_Pinky3",
            "position": {
                "x": 0.02192234992980957,
                "y": 0.001216089352965355,
                "z": 0.00024647824466228485
            },
            "rotation": {
                "x": -1.490114875934978e-8,
                "y": 2.980229751869956e-8,
                "z": 2.980229751869956e-8,
                "w": 1.0
            }
        }
    ]
}